auto_run_on_remote/__init__.py
auto_run_on_remote/paramiko_util.py
auto_run_on_remote/remote_config.py
auto_run_on_remote/run_script_on_remote_server.py
auto_run_on_remote/set_config.py
auto_run_on_remote-0.5.dist-info/METADATA
auto_run_on_remote-0.5.dist-info/WHEEL
auto_run_on_remote-0.5.dist-info/top_level.txt
auto_run_on_remote-0.5.dist-info/RECORD
